tictectoc/__init__.py
tictectoc/tictectoc.py
tictectoc-0.1.4.dist-info/LICENSE
tictectoc-0.1.4.dist-info/METADATA
tictectoc-0.1.4.dist-info/WHEEL
tictectoc-0.1.4.dist-info/top_level.txt
tictectoc-0.1.4.dist-info/RECORD
