Metadata-Version: 2.1
Name: tictectoc
Version: 0.1.4
Summary: Tic Tec Toc timing for Python
Home-page: https://github.com/nemodleo/tictectoc
Author: Hyun Park
Author-email: nemod.leo@snu.ac.kr
License: MIT
Keywords: tic tec toc tictoc tictectoc time timing
Classifier: License :: OSI Approved :: MIT License
Requires-Python: >= 3.6
License-File: LICENSE
